[{"name":"passport_auth_status","value":"238fd5baaa62d5e3a98bc41fe46ccfc4%2C","domain":".douyin.com","path":"/","expires":1631673878.911624,"size":55,"httpOnly":true,"secure":false,"session":false,"sameParty":false,"sourceScheme":"Secure","sourcePort":443},{"name":"sessionid_ss","value":"0913bc79fa6ba0248d6d282503ad1d2e","domain":".douyin.com","path":"/","expires":1634265877.911555,"size":44,"httpOnly":true,"secure":true,"session":false,"sameSite":"None","sameParty":false,"sourceScheme":"Secure","sourcePort":443},{"name":"sid_tt","value":"0913bc79fa6ba0248d6d282503ad1d2e","domain":".douyin.com","path":"/","expires":1634265877.911512,"size":38,"httpOnly":true,"secure":false,"session":false,"sameParty":false,"sourceScheme":"Secure","sourcePort":443},{"name":"uid_tt_ss","value":"ac886106ae80861772664aed61b253df","domain":".douyin.com","path":"/","expires":1634265877.91149,"size":41,"httpOnly":true,"secure":true,"session":false,"sameSite":"None","sameParty":false,"sourceScheme":"Secure","sourcePort":443},{"name":"ssid_ucp_v1","value":"1.0.0-KDliY2Q0NzQyYzAxMzczNGZjZTNiNmMyYTdmMWQ2NjYxNmRmZjQ1YzEKFwjTveCTgPX3ARCXoueIBhiWTjgGQPQHGgJsZiIgMDkxM2JjNzlmYTZiYTAyNDhkNmQyODI1MDNhZDFkMmU","domain":".douyin.com","path":"/","expires":1634265877.911599,"size":156,"httpOnly":true,"secure":true,"session":false,"sameSite":"None","sameParty":false,"sourceScheme":"Secure","sourcePort":443},{"name":"sessionid","value":"0913bc79fa6ba0248d6d282503ad1d2e","domain":".douyin.com","path":"/","expires":1634265877.911533,"size":41,"httpOnly":true,"secure":false,"session":false,"sameParty":false,"sourceScheme":"Secure","sourcePort":443},{"name":"uid_tt","value":"ac886106ae80861772664aed61b253df","domain":".douyin.com","path":"/","expires":1634265877.911467,"size":38,"httpOnly":true,"secure":false,"session":false,"sameParty":false,"sourceScheme":"Secure","sourcePort":443},{"name":"sid_guard","value":"0913bc79fa6ba0248d6d282503ad1d2e%7C1629081879%7C5183999%7CFri%2C+15-Oct-2021+02%3A44%3A38+GMT","domain":".douyin.com","path":"/","expires":1660185878.911437,"size":102,"httpOnly":true,"secure":false,"session":false,"sameParty":false,"sourceScheme":"Secure","sourcePort":443},{"name":"n_mh","value":"9-mIeuD4wZnlYrrOvfzG3MuT6aQmCUtmr8FxV8Kl8xY","domain":".douyin.com","path":"/","expires":1639449878.684979,"size":47,"httpOnly":true,"secure":false,"session":false,"sameParty":false,"sourceScheme":"Secure","sourcePort":443},{"name":"toutiao_sso_user","value":"6932f218f66b8cc164c083447c5acb06","domain":".douyin.com","path":"/","expires":1634265878.684949,"size":48,"httpOnly":true,"secure":false,"session":false,"sameParty":false,"sourceScheme":"Secure","sourcePort":443},{"name":"sso_uid_tt_ss","value":"b5477c4ea86f9e3fe4232eb00cae1ef0","domain":".douyin.com","path":"/","expires":1634265878.684929,"size":45,"httpOnly":true,"secure":true,"session":false,"sameSite":"None","sameParty":false,"sourceScheme":"Secure","sourcePort":443},{"name":"sso_uid_tt","value":"b5477c4ea86f9e3fe4232eb00cae1ef0","domain":".douyin.com","path":"/","expires":1634265878.684894,"size":42,"httpOnly":true,"secure":false,"session":false,"sameParty":false,"sourceScheme":"Secure","sourcePort":443},{"name":"passport_csrf_token","value":"606a51a5230e162defcc1df1e526ca27","domain":".douyin.com","path":"/","expires":1634265863.473467,"size":51,"httpOnly":false,"secure":true,"session":false,"sameSite":"None","sameParty":false,"sourceScheme":"Secure","sourcePort":443},{"name":"sid_ucp_v1","value":"1.0.0-KDliY2Q0NzQyYzAxMzczNGZjZTNiNmMyYTdmMWQ2NjYxNmRmZjQ1YzEKFwjTveCTgPX3ARCXoueIBhiWTjgGQPQHGgJsZiIgMDkxM2JjNzlmYTZiYTAyNDhkNmQyODI1MDNhZDFkMmU","domain":".douyin.com","path":"/","expires":1634265877.911576,"size":155,"httpOnly":true,"secure":true,"session":false,"sameParty":false,"sourceScheme":"Secure","sourcePort":443},{"name":"passport_auth_status_ss","value":"238fd5baaa62d5e3a98bc41fe46ccfc4%2C","domain":".douyin.com","path":"/","expires":1631673878.91138,"size":58,"httpOnly":true,"secure":true,"session":false,"sameSite":"None","sameParty":false,"sourceScheme":"Secure","sourcePort":443},{"name":"toutiao_sso_user_ss","value":"6932f218f66b8cc164c083447c5acb06","domain":".douyin.com","path":"/","expires":1634265878.684964,"size":51,"httpOnly":true,"secure":true,"session":false,"sameSite":"None","sameParty":false,"sourceScheme":"Secure","sourcePort":443},{"name":"MONITOR_WEB_ID","value":"2502ff27-2091-4cbd-b173-7449bcf699da","domain":".www.douyin.com","path":"/","expires":1636857863.032486,"size":50,"httpOnly":false,"secure":false,"session":false,"sameParty":false,"sourceScheme":"Secure","sourcePort":443},{"name":"passport_csrf_token_default","value":"606a51a5230e162defcc1df1e526ca27","domain":".douyin.com","path":"/","expires":1634265863.473438,"size":59,"httpOnly":false,"secure":false,"session":false,"sameParty":false,"sourceScheme":"Secure","sourcePort":443},{"name":"s_v_web_id","value":"verify_kse1a28z_gVJnYNzV_4uF7_4APj_Addf_yaDyY6pXZjEW","domain":"www.douyin.com","path":"/","expires":-1,"size":62,"httpOnly":false,"secure":false,"session":true,"sameParty":false,"sourceScheme":"Secure","sourcePort":443}]